webpack_loader_remote/__init__.py
webpack_loader_remote/apps.py
webpack_loader_remote/config.py
webpack_loader_remote/errors.py
webpack_loader_remote/exceptions.py
webpack_loader_remote/loader.py
webpack_loader_remote/signals.py
webpack_loader_remote/utils.py
webpack_loader_remote/contrib/__init__.py
webpack_loader_remote/contrib/jinja2ext.py
webpack_loader_remote/templatetags/__init__.py
webpack_loader_remote/templatetags/webpack_loader_remote.py
django_webpack_loader_remote-2.0.0.dist-info/LICENSE.txt
django_webpack_loader_remote-2.0.0.dist-info/METADATA
django_webpack_loader_remote-2.0.0.dist-info/WHEEL
django_webpack_loader_remote-2.0.0.dist-info/top_level.txt
django_webpack_loader_remote-2.0.0.dist-info/RECORD
