Metadata-Version: 2.1
Name: django-webpack-loader-remote
Version: 2.0.0
Summary: Load webpack assets from a local or remote stats file
Home-page: https://github.com/alexseitsinger/django-webpack-loader-remote
Author: Alex Seitsinger
Author-email: software@alexseitsinger.com
License: BSD 2-Clause License
Project-URL: Documentation, https://github.com/alexseitsinger/django-webpack-loader-remote
Project-URL: Source, https://github.com/alexseitsinger/django-webpack-loader-remote
Project-URL: Tracker, https://github.com/alexseitsinger/django-webpack-loader-remote/issues
Keywords: django,webpack
Platform: UNKNOWN
Classifier: Development Status :: 5 - Production/Stable
Classifier: Environment :: Web Environment
Classifier: Framework :: Django
Classifier: Intended Audience :: Developers
Classifier: License :: OSI Approved :: BSD License
Classifier: Natural Language :: English
Classifier: Operating System :: OS Independent
Classifier: Programming Language :: Python :: 2
Classifier: Programming Language :: Python :: 3
Classifier: Topic :: Internet :: WWW/HTTP :: Dynamic Content :: Content Management System
